Metadata-Version: 2.1
Name: yandex-music-utilities
Version: 1.0.0
Summary: This package allows you to download music asynchronously and check playlists for deleted music
Author: Dmitry Polulyakh
Author-email: dmitry_korj@icloud.com
Classifier: Programming Language :: Python :: 3
Classifier: License :: OSI Approved :: MIT License
Classifier: Operating System :: OS Independent
Requires-Python: >=3.8
